{"imagePath":"Esferas_tex.png","name":"Orbs_tex","SubTexture":[{"frameHeight":259,"y":1,"frameX":0,"width":258,"frameY":0,"height":258,"name":"Cintilando_0","frameWidth":259,"x":781},{"frameHeight":259,"y":1,"frameX":0,"width":258,"frameY":0,"height":258,"name":"Cintilando_1","frameWidth":259,"x":1561},{"frameHeight":259,"y":1,"frameX":0,"width":258,"frameY":0,"height":258,"name":"Cintilando_2","frameWidth":259,"x":1},{"frameHeight":259,"y":261,"frameX":0,"width":258,"frameY":0,"height":258,"name":"Cintilando_3","frameWidth":259,"x":521},{"frameHeight":259,"y":1,"frameX":0,"width":258,"frameY":0,"height":258,"name":"Cintilando_4","frameWidth":259,"x":1041},{"frameHeight":259,"y":521,"frameX":0,"width":258,"frameY":0,"height":258,"name":"Cintilando_5","frameWidth":259,"x":1041},{"frameHeight":259,"y":1,"frameX":0,"width":258,"frameY":0,"height":258,"name":"Cintilando_6","frameWidth":259,"x":1301},{"frameHeight":259,"y":261,"frameX":0,"width":258,"frameY":0,"height":258,"name":"Cintilando_7","frameWidth":259,"x":261},{"frameHeight":259,"y":261,"frameX":0,"width":258,"frameY":0,"height":258,"name":"Cintilando_8","frameWidth":259,"x":781},{"frameHeight":259,"y":261,"frameX":0,"width":258,"frameY":0,"height":258,"name":"Cintilando_9","frameWidth":259,"x":1041},{"frameHeight":259,"y":521,"frameX":0,"width":258,"frameY":0,"height":258,"name":"Cintilando_10","frameWidth":259,"x":781},{"frameHeight":259,"y":521,"frameX":0,"width":258,"frameY":0,"height":258,"name":"Cintilando_11","frameWidth":259,"x":521},{"frameHeight":259,"y":521,"frameX":0,"width":258,"frameY":0,"height":258,"name":"Cintilando_12","frameWidth":259,"x":261},{"frameHeight":259,"y":1,"frameX":0,"width":258,"frameY":0,"height":258,"name":"Cintilando_13","frameWidth":259,"x":521},{"frameHeight":259,"y":521,"frameX":0,"width":258,"frameY":0,"height":258,"name":"Cintilando_14","frameWidth":259,"x":1},{"frameHeight":259,"y":261,"frameX":0,"width":258,"frameY":0,"height":258,"name":"Cintilando_15","frameWidth":259,"x":1},{"frameHeight":259,"y":1,"frameX":0,"width":258,"frameY":0,"height":258,"name":"_Cintilando_0","frameWidth":259,"x":261}]}